Metadata-Version: 2.1
Name: descript-audiotools-unofficial
Version: 0.7.4
Summary: Utilities for handling audio.
Author: Prem Seetharaman, Lucas Gestin
Author-email: prem@descript.com
License: MIT
Classifier: Intended Audience :: Developers
Classifier: Intended Audience :: Education
Classifier: Intended Audience :: Science/Research
Classifier: Natural Language :: English
Classifier: Programming Language :: Python :: 3.7
Classifier: Topic :: Artistic Software
Classifier: Topic :: Multimedia
Classifier: Topic :: Multimedia :: Sound/Audio
Classifier: Topic :: Multimedia :: Sound/Audio :: Editors
Classifier: Topic :: Software Development :: Libraries
License-File: LICENSE
Requires-Dist: argbind
Requires-Dist: numpy
Requires-Dist: soundfile
Requires-Dist: pyloudnorm
Requires-Dist: importlib-resources
Requires-Dist: scipy
Requires-Dist: torch
Requires-Dist: julius
Requires-Dist: torchaudio
Requires-Dist: ffmpy
Requires-Dist: ipython
Requires-Dist: rich
Requires-Dist: matplotlib
Requires-Dist: librosa
Requires-Dist: pystoi
Requires-Dist: torch_stoi
Requires-Dist: flatten-dict
Requires-Dist: markdown2
Requires-Dist: randomname
Requires-Dist: protobuf!=4.24.0,<5.0.0,>=3.19.6
Requires-Dist: tensorboard
Requires-Dist: tqdm
Provides-Extra: tests
Requires-Dist: pytest; extra == "tests"
Requires-Dist: pytest-cov; extra == "tests"
Requires-Dist: line_profiler; extra == "tests"
Requires-Dist: pesq; extra == "tests"
Requires-Dist: gradio==3.32.0; extra == "tests"
Requires-Dist: transformers>=4.23.1; extra == "tests"
Provides-Extra: docs
Requires-Dist: sphinx; extra == "docs"
Requires-Dist: sphinx-rtd-theme; extra == "docs"
Requires-Dist: myst-parser; extra == "docs"
Requires-Dist: myst-nb; extra == "docs"
Requires-Dist: sphinx-multiversion; extra == "docs"
Provides-Extra: whisper
Requires-Dist: transformers>=4.23.1; extra == "whisper"
